odoo10_addon_purchase_request_department-10.0.1.0.0.99.dev1-py2.7-nspkg.pth
odoo/addons/purchase_request_department/README.rst
odoo/addons/purchase_request_department/__init__.py
odoo/addons/purchase_request_department/__manifest__.py
odoo/addons/purchase_request_department/hooks.py
odoo/addons/purchase_request_department/i18n/de.po
odoo/addons/purchase_request_department/i18n/es.po
odoo/addons/purchase_request_department/i18n/fr.po
odoo/addons/purchase_request_department/i18n/hr.po
odoo/addons/purchase_request_department/i18n/it.po
odoo/addons/purchase_request_department/i18n/nb.po
odoo/addons/purchase_request_department/i18n/nb_NO.po
odoo/addons/purchase_request_department/i18n/pt_BR.po
odoo/addons/purchase_request_department/i18n/purchase_request_department.pot
odoo/addons/purchase_request_department/i18n/sl.po
odoo/addons/purchase_request_department/i18n/tr.po
odoo/addons/purchase_request_department/models/__init__.py
odoo/addons/purchase_request_department/models/purchase_request.py
odoo/addons/purchase_request_department/static/description/icon.png
odoo/addons/purchase_request_department/tests/__init__.py
odoo/addons/purchase_request_department/tests/test_purchase_request_department.py
odoo/addons/purchase_request_department/views/purchase_request_department_view.xml
odoo10_addon_purchase_request_department-10.0.1.0.0.99.dev1.dist-info/METADATA
odoo10_addon_purchase_request_department-10.0.1.0.0.99.dev1.dist-info/RECORD
odoo10_addon_purchase_request_department-10.0.1.0.0.99.dev1.dist-info/WHEEL
odoo10_addon_purchase_request_department-10.0.1.0.0.99.dev1.dist-info/namespace_packages.txt
odoo10_addon_purchase_request_department-10.0.1.0.0.99.dev1.dist-info/top_level.txt
